MANIFEST.in
README.md
pyproject.toml
setup.py
tests.py
cysqlite.egg-info/PKG-INFO
cysqlite.egg-info/SOURCES.txt
cysqlite.egg-info/dependency_links.txt
cysqlite.egg-info/not-zip-safe
cysqlite.egg-info/top_level.txt
src/cysqlite.c
src/cysqlite.pxd
src/cysqlite.pyx
src/sqlite3.pxi