Metadata-Version: 2.4
Name: cysqlite
Version: 0.1.0
Summary: bindings for sqlite3
Author-email: Charles Leifer <coleifer@gmail.com>
Project-URL: Homepage, https://github.com/coleifer/cysqlite
Project-URL: Repository, https://github.com/coleifer/cysqlite
Classifier: Programming Language :: Python :: 2
Classifier: Programming Language :: Python :: 3
Classifier: Topic :: Database :: Database Engines/Servers
Classifier: Topic :: Software Development :: Embedded Systems
Classifier: Topic :: Software Development :: Libraries :: Python Modules
